pptx_merger/__init__.py
pptx_merger/core.py
pptx_merger/lib/DocumentFormat.OpenXml.dll
pptx_merger/lib/OpenXmlPowerTools.dll
pptx_merger/lib/System.Drawing.Common.dll
pptx_merger/lib/System.IO.Packaging.dll
python_pptx_merger-0.0.2.dist-info/METADATA
python_pptx_merger-0.0.2.dist-info/WHEEL
python_pptx_merger-0.0.2.dist-info/licenses/LICENSE
python_pptx_merger-0.0.2.dist-info/RECORD
