Metadata-Version: 2.4
Name: python-pptx-merger
Version: 0.0.2
Summary: Merge PowerPoint (.pptx) files
Project-URL: Homepage, https://github.com/Tailen/python-pptx-merger
Project-URL: Issues, https://github.com/Tailen/python-pptx-merger/issues
Author-email: Hao Mei <wuximeihao@gmail.com>
License-Expression: MIT
License-File: LICENSE
Keywords: office,openxml,powerpoint,ppt,pptx
Classifier: License :: OSI Approved :: MIT License
Classifier: Operating System :: OS Independent
Classifier: Programming Language :: Python :: 3
Classifier: Programming Language :: Python :: 3.9
Classifier: Programming Language :: Python :: 3.10
Classifier: Programming Language :: Python :: 3.11
Classifier: Programming Language :: Python :: 3.12
Classifier: Programming Language :: Python :: 3.13
Classifier: Topic :: Office/Business :: Office Suites
Classifier: Topic :: Software Development :: Libraries
Requires-Python: >=3.9
Requires-Dist: pythonnet>=3.0.5
